Workbook

Sheet Guía
A1: Gestión de tienda – Guía rápida
A3: CÓMO USAR ESTE LIBRO
A4: 1. Config: pon el nombre de tu tienda, el año y ajusta categorías y métodos de pago.
A5: 2. Productos: registra cada producto UNA vez (nombre y código únicos, categoría, costo, precio, cantidad inicial y mínima en el almacén).
A6: 3. Compras: elige el Producto en la lista, escribe Fecha y Cantidad. El código, proveedor y costo se completan solos.
A7: 4. Ventas: elige el Producto en la lista, escribe Fecha, N° venta, Cantidad, Descuento y Método de pago. El código, categoría y precio se completan solos.
A8: Si una venta tiene varios productos, usa el mismo N° de venta en varias filas.
A9: 5. Inventario: se calcula solo. Marca REPONER cuando la cantidad llega al mínimo y AGOTADO cuando se acaba.
A10: 6. Resumen: totales, ganancia, valor del inventario, resultados por categoría y evolución mensual (con gráficos).
A12: CÓDIGO DE COLORES
A13: Texto azul = celdas que tú rellenas. Texto negro = fórmulas (no tocar). Fila azul claro = totales (arriba de cada tabla).
A15: NOTAS
... A21: • Las cifras no llevan símbolo de moneda; usa la de tu país.

Sheet Resumen
A1: =Config!B3&" – Panel de resumen" -> Mi Tienda – Panel de resumen
A2: ="Año de análisis: "&Config!B4&" | Todo se calcula automáticamente desde Ventas, Compras e Inventario" -> Año de análisis: 2026 | Todo se calcula automáticamente desde Ventas, Compras e Inventario
A4: INDICADORES CLAVE | D4: VENTAS POR MÉTODO DE PAGO
A5: Ventas totales | B5: =Ventas!I3 -> 285.06 | D5: Método | E5: N° ventas | F5: Total
A6: Compras totales | B6: =Compras!G3 -> 333.9 | D6: =Config!F4 -> Efectivo | E6: =COUNTIF(Ventas!$J$5:$J$504,D6) -> 9 | F6: =SUMIFS(Ventas!$I$5:$I$504,Ventas!$J$5:$J$504,D6) -> 152.8
A7: Costo de lo vendido | B7: =Ventas!L3 -> 166.95 | D7: =Config!F5 -> Transferencia | E7: =COUNTIF(Ventas!$J$5:$J$504,D7) -> 7 | F7: =SUMIFS(Ventas!$I$5:$I$504,Ventas!$J$5:$J$504,D7) -> 132.26
A8: Ganancia bruta | B8: =Ventas!M3 -> 118.11 | D8: Total | E8: =SUM(E6:E7) -> 16 | F8: =SUM(F6:F7) -> 285.06
A9: Margen bruto % | B9: =IF(B5=0,0,B8/B5) -> 0.41433382
A10: Valor del inventario (a costo) | B10: =Inventario!K3 -> 814.15
A11: Valor del inventario (a precio de venta) | B11: =Inventario!L3 -> 1377.9
A12: Unidades vendidas | B12: =Ventas!F3 -> 124
A13: Productos en catálogo | B13: =COUNTIF(Productos!B5:B104,"?*") -> 12
A14: Productos a reponer / agotados | B14: =COUNTIF(Inventario!I5:I104,"REPONER")+COUNTIF(Inventario!I5:I104,"AGOTADO") -> 1
A17: RESULTADOS POR CATEGORÍA
A18: Categoría | B18: Unidades vendidas | C18: Ventas | D18: Ganancia bruta | E18: Valor inventario (costo)
A19: =Config!D4 -> Alimentos | B19: =SUMIFS(Ventas!$F$5:$F$504,Ventas!$E$5:$E$504,A19) -> 18 | C19: =SUMIFS(Ventas!$I$5:$I$504,Ventas!$E$5:$E$504,A19) -> 54 | D19: =SUMIFS(Ventas!$M$5:$M$504,Ventas!$E$5:$E$504,A19) -> 19.8 | E19: =SUMIFS(Inventario!$K$5:$K$104,Inventario!$C$5:$C$104,A19) -> 271.8
A20: =Config!D5 -> Lácteos | B20: =SUMIFS(Ventas!$F$5:$F$504,Ventas!$E$5:$E$504,A20) -> 39 | C20: =SUMIFS(Ventas!$I$5:$I$504,Ventas!$E$5:$E$504,A20) -> 47.35 | D20: =SUMIFS(Ventas!$M$5:$M$504,Ventas!$E$5:$E$504,A20) -> 18.4 | E20: =SUMIFS(Inventario!$K$5:$K$104,Inventario!$C$5:$C$104,A20) -> 93.05
A21: =Config!D6 -> Bebidas | B21: =SUMIFS(Ventas!$F$5:$F$504,Ventas!$E$5:$E$504,A21) -> 28 | C21: =SUMIFS(Ventas!$I$5:$I$504,Ventas!$E$5:$E$504,A21) -> 35.41 | D21: =SUMIFS(Ventas!$M$5:$M$504,Ventas!$E$5:$E$504,A21) -> 15.81 | E21: =SUMIFS(Inventario!$K$5:$K$104,Inventario!$C$5:$C$104,A21) -> 97.4
A22: =Config!D7 -> Limpieza | B22: =SUMIFS(Ventas!$F$5:$F$504,Ventas!$E$5:$E$504,A22) -> 10 | C22: =SUMIFS(Ventas!$I$5:$I$504,Ventas!$E$5:$E$504,A22) -> 67.7 | D22: =SUMIFS(Ventas!$M$5:$M$504,Ventas!$E$5:$E$504,A22) -> 24.7 | E22: =SUMIFS(Inventario!$K$5:$K$104,Inventario!$C$5:$C$104,A22) -> 208.4
A23: =Config!D8 -> Snacks | B23: =SUMIFS(Ventas!$F$5:$F$504,Ventas!$E$5:$E$504,A23) -> 16 | C23: =SUMIFS(Ventas!$I$5:$I$504,Ventas!$E$5:$E$504,A23) -> 31.2 | D23: =SUMIFS(Ventas!$M$5:$M$504,Ventas!$E$5:$E$504,A23) -> 14.5 | E23: =SUMIFS(Inventario!$K$5:$K$104,Inventario!$C$5:$C$104,A23) -> 121.8
A24: =Config!D9 -> Papelería | B24: =SUMIFS(Ventas!$F$5:$F$504,Ventas!$E$5:$E$504,A24) -> 13 | C24: =SUMIFS(Ventas!$I$5:$I$504,Ventas!$E$5:$E$504,A24) -> 49.4 | D24: =SUMIFS(Ventas!$M$5:$M$504,Ventas!$E$5:$E$504,A24) -> 24.9 | E24: =SUMIFS(Inventario!$K$5:$K$104,Inventario!$C$5:$C$104,A24) -> 21.7
A25: =Config!D10 -> Higiene personal | B25: =SUMIFS(Ventas!$F$5:$F$504,Ventas!$E$5:$E$504,A25) -> 0 | C25: =SUMIFS(Ventas!$I$5:$I$504,Ventas!$E$5:$E$504,A25) -> 0 | D25: =SUMIFS(Ventas!$M$5:$M$504,Ventas!$E$5:$E$504,A25) -> 0 | E25: =SUMIFS(Inventario!$K$5:$K$104,Inventario!$C$5:$C$104,A25) -> 0
A26: =Config!D11 -> Otros | B26: =SUMIFS(Ventas!$F$5:$F$504,Ventas!$E$5:$E$504,A26) -> 0 | C26: =SUMIFS(Ventas!$I$5:$I$504,Ventas!$E$5:$E$504,A26) -> 0 | D26: =SUMIFS(Ventas!$M$5:$M$504,Ventas!$E$5:$E$504,A26) -> 0 | E26: =SUMIFS(Inventario!$K$5:$K$104,Inventario!$C$5:$C$104,A26) -> 0
A27: Total | B27: =SUM(B19:B26) -> 124 | C27: =SUM(C19:C26) -> 285.06 | D27: =SUM(D19:D26) -> 118.11 | E27: =SUM(E19:E26) -> 814.15
A30: EVOLUCIÓN MENSUAL
A31: Mes | B31: Ventas | C31: Compras | D31: Ganancia bruta
A32: Enero | B32: =SUMIFS(Ventas!$I$5:$I$504,Ventas!$A$5:$A$504,">="&DATE(Config!$B$4,1,1),Ventas!$A$5:$A$504,"<"&DATE(Config!$B$4,2,1)) -> 0 | C32: =SUMIFS(Compras!$G$5:$G$304,Compras!$A$5:$A$304,">="&DATE(Config!$B$4,1,1),Compras!$A$5:$A$304,"<"&DATE(Config!$B$4,2,1)) -> 0 | D32: =SUMIFS(Ventas!$M$5:$M$504,Ventas!$A$5:$A$504,">="&DATE(Config!$B$4,1,1),Ventas!$A$5:$A$504,"<"&DATE(Config!$B$4,2,1)) -> 0
A33: Febrero | B33: =SUMIFS(Ventas!$I$5:$I$504,Ventas!$A$5:$A$504,">="&DATE(Config!$B$4,2,1),Ventas!$A$5:$A$504,"<"&DATE(Config!$B$4,3,1)) -> 0 | C33: =SUMIFS(Compras!$G$5:$G$304,Compras!$A$5:$A$304,">="&DATE(Config!$B$4,2,1),Compras!$A$5:$A$304,"<"&DATE(Config!$B$4,3,1)) -> 0 | D33: =SUMIFS(Ventas!$M$5:$M$504,Ventas!$A$5:$A$504,">="&DATE(Config!$B$4,2,1),Ventas!$A$5:$A$504,"<"&DATE(Config!$B$4,3,1)) -> 0
A34: Marzo | B34: =SUMIFS(Ventas!$I$5:$I$504,Ventas!$A$5:$A$504,">="&DATE(Config!$B$4,3,1),Ventas!$A$5:$A$504,"<"&DATE(Config!$B$4,4,1)) -> 0 | C34: =SUMIFS(Compras!$G$5:$G$304,Compras!$A$5:$A$304,">="&DATE(Config!$B$4,3,1),Compras!$A$5:$A$304,"<"&DATE(Config!$B$4,4,1)) -> 0 | D34: =SUMIFS(Ventas!$M$5:$M$504,Ventas!$A$5:$A$504,">="&DATE(Config!$B$4,3,1),Ventas!$A$5:$A$504,"<"&DATE(Config!$B$4,4,1)) -> 0
A35: Abril | B35: =SUMIFS(Ventas!$I$5:$I$504,Ventas!$A$5:$A$504,">="&DATE(Config!$B$4,4,1),Ventas!$A$5:$A$504,"<"&DATE(Config!$B$4,5,1)) -> 0 | C35: =SUMIFS(Compras!$G$5:$G$304,Compras!$A$5:$A$304,">="&DATE(Config!$B$4,4,1),Compras!$A$5:$A$304,"<"&DATE(Config!$B$4,5,1)) -> 0 | D35: =SUMIFS(Ventas!$M$5:$M$504,Ventas!$A$5:$A$504,">="&DATE(Config!$B$4,4,1),Ventas!$A$5:$A$504,"<"&DATE(Config!$B$4,5,1)) -> 0
A36: Mayo | B36: =SUMIFS(Ventas!$I$5:$I$504,Ventas!$A$5:$A$504,">="&DATE(Config!$B$4,5,1),Ventas!$A$5:$A$504,"<"&DATE(Config!$B$4,6,1)) -> 0 | C36: =SUMIFS(Compras!$G$5:$G$304,Compras!$A$5:$A$304,">="&DATE(Config!$B$4,5,1),Compras!$A$5:$A$304,"<"&DATE(Config!$B$4,6,1)) -> 0 | D36: =SUMIFS(Ventas!$M$5:$M$504,Ventas!$A$5:$A$504,">="&DATE(Config!$B$4,5,1),Ventas!$A$5:$A$504,"<"&DATE(Config!$B$4,6,1)) -> 0
A37: Junio | B37: =SUMIFS(Ventas!$I$5:$I$504,Ventas!$A$5:$A$504,">="&DATE(Config!$B$4,6,1),Ventas!$A$5:$A$504,"<"&DATE(Config!$B$4,7,1)) -> 0 | C37: =SUMIFS(Compras!$G$5:$G$304,Compras!$A$5:$A$304,">="&DATE(Config!$B$4,6,1),Compras!$A$5:$A$304,"<"&DATE(Config!$B$4,7,1)) -> 0 | D37: =SUMIFS(Ventas!$M$5:$M$504,Ventas!$A$5:$A$504,">="&DATE(Config!$B$4,6,1),Ventas!$A$5:$A$504,"<"&DATE(Config!$B$4,7,1)) -> 0
A38: Julio | B38: =SUMIFS(Ventas!$I$5:$I$504,Ventas!$A$5:$A$504,">="&DATE(Config!$B$4,7,1),Ventas!$A$5:$A$504,"<"&DATE(Config!$B$4,8,1)) -> 0 | C38: =SUMIFS(Compras!$G$5:$G$304,Compras!$A$5:$A$304,">="&DATE(Config!$B$4,7,1),Compras!$A$5:$A$304,"<"&DATE(Config!$B$4,8,1)) -> 0 | D38: =SUMIFS(Ventas!$M$5:$M$504,Ventas!$A$5:$A$504,">="&DATE(Config!$B$4,7,1),Ventas!$A$5:$A$504,"<"&DATE(Config!$B$4,8,1)) -> 0
A39: Agosto | B39: =SUMIFS(Ventas!$I$5:$I$504,Ventas!$A$5:$A$504,">="&DATE(Config!$B$4,8,1),Ventas!$A$5:$A$504,"<"&DATE(Config!$B$4,9,1)) -> 0 | C39: =SUMIFS(Compras!$G$5:$G$304,Compras!$A$5:$A$304,">="&DATE(Config!$B$4,8,1),Compras!$A$5:$A$304,"<"&DATE(Config!$B$4,9,1)) -> 0 | D39: =SUMIFS(Ventas!$M$5:$M$504,Ventas!$A$5:$A$504,">="&DATE(Config!$B$4,8,1),Ventas!$A$5:$A$504,"<"&DATE(Config!$B$4,9,1)) -> 0
A40: Septiembre | B40: =SUMIFS(Ventas!$I$5:$I$504,Ventas!$A$5:$A$504,">="&DATE(Config!$B$4,9,1),Ventas!$A$5:$A$504,"<"&DATE(Config!$B$4,10,1)) -> 119.51 | C40: =SUMIFS(Compras!$G$5:$G$304,Compras!$A$5:$A$304,">="&DATE(Config!$B$4,9,1),Compras!$A$5:$A$304,"<"&DATE(Config!$B$4,10,1)) -> 197.4 | D40: =SUMIFS(Ventas!$M$5:$M$504,Ventas!$A$5:$A$504,">="&DATE(Config!$B$4,9,1),Ventas!$A$5:$A$504,"<"&DATE(Config!$B$4,10,1)) -> 50.11
A41: Octubre | B41: =SUMIFS(Ventas!$I$5:$I$504,Ventas!$A$5:$A$504,">="&DATE(Config!$B$4,10,1),Ventas!$A$5:$A$504,"<"&DATE(Config!$B$4,11,1)) -> 165.55 | C41: =SUMIFS(Compras!$G$5:$G$304,Compras!$A$5:$A$304,">="&DATE(Config!$B$4,10,1),Compras!$A$5:$A$304,"<"&DATE(Config!$B$4,11,1)) -> 136.5 | D41: =SUMIFS(Ventas!$M$5:$M$504,Ventas!$A$5:$A$504,">="&DATE(Config!$B$4,10,1),Ventas!$A$5:$A$504,"<"&DATE(Config!$B$4,11,1)) -> 68
A42: Noviembre | B42: =SUMIFS(Ventas!$I$5:$I$504,Ventas!$A$5:$A$504,">="&DATE(Config!$B$4,11,1),Ventas!$A$5:$A$504,"<"&DATE(Config!$B$4,12,1)) -> 0 | C42: =SUMIFS(Compras!$G$5:$G$304,Compras!$A$5:$A$304,">="&DATE(Config!$B$4,11,1),Compras!$A$5:$A$304,"<"&DATE(Config!$B$4,12,1)) -> 0 | D42: =SUMIFS(Ventas!$M$5:$M$504,Ventas!$A$5:$A$504,">="&DATE(Config!$B$4,11,1),Ventas!$A$5:$A$504,"<"&DATE(Config!$B$4,12,1)) -> 0
A43: Diciembre | B43: =SUMIFS(Ventas!$I$5:$I$504,Ventas!$A$5:$A$504,">="&DATE(Config!$B$4,12,1),Ventas!$A$5:$A$504,"<"&DATE(Config!$B$4,13,1)) -> 0 | C43: =SUMIFS(Compras!$G$5:$G$304,Compras!$A$5:$A$304,">="&DATE(Config!$B$4,12,1),Compras!$A$5:$A$304,"<"&DATE(Config!$B$4,13,1)) -> 0 | D43: =SUMIFS(Ventas!$M$5:$M$504,Ventas!$A$5:$A$504,">="&DATE(Config!$B$4,12,1),Ventas!$A$5:$A$504,"<"&DATE(Config!$B$4,13,1)) -> 0
A44: Total año | B44: =SUM(B32:B43) -> 285.06 | C44: =SUM(C32:C43) -> 333.9 | D44: =SUM(D32:D43) -> 118.11

Sheet Productos
A1: Catálogo de productos
A2: Registra cada producto una sola vez (nombre y código únicos). Los demás libros leen estos datos.
A4: Código | B4: Producto | C4: Categoría | D4: Proveedor | E4: Cantidad inicial en el almacén | F4: Costo unitario | G4: Precio de venta | H4: Margen unitario | I4: Margen % | J4: Cantidad mínima en el almacén
A5: P001 | B5: Arroz 1 kg | C5: Alimentos | D5: Distribuidora Norte | E5: 50 | F5: 0.9 | G5: 1.5 | H5: =IF(B5="","",G5-F5) -> 0.6 | I5: =IF(OR(B5="",G5=0),"",H5/G5) -> 0.4 | J5: 15
A6: P002 | B6: Aceite de oliva 1 L | C6: Alimentos | D6: Distribuidora Norte | E6: 30 | F6: 4.5 | G6: 6.9 | H6: =IF(B6="","",G6-F6) -> 2.4 | I6: =IF(OR(B6="",G6=0),"",H6/G6) -> 0.34782609 | J6: 10
A7: P003 | B7: Leche entera 1 L | C7: Lácteos | D7: Lácteos del Sur | E7: 60 | F7: 0.65 | G7: 1.05 | H7: =IF(B7="","",G7-F7) -> 0.4 | I7: =IF(OR(B7="",G7=0),"",H7/G7) -> 0.38095238 | J7: 20
A8: P004 | B8: Yogur natural (pack 4) | C8: Lácteos | D8: Lácteos del Sur | E8: 40 | F8: 1.1 | G8: 1.85 | H8: =IF(B8="","",G8-F8) -> 0.75 | I8: =IF(OR(B8="",G8=0),"",H8/G8) -> 0.40540541 | J8: 12
A9: P005 | B9: Refresco cola 2 L | C9: Bebidas | D9: Bebidas Central | E9: 45 | F9: 1 | G9: 1.75 | H9: =IF(B9="","",G9-F9) -> 0.75 | I9: =IF(OR(B9="",G9=0),"",H9/G9) -> 0.42857143 | J9: 15
A10: P006 | B10: Agua mineral 1,5 L | C10: Bebidas | D10: Bebidas Central | E10: 80 | F10: 0.3 | G10: 0.65 | H10: =IF(B10="","",G10-F10) -> 0.35 | I10: =IF(OR(B10="",G10=0),"",H10/G10) -> 0.53846154 | J10: 30
A11: P007 | B11: Detergente 3 L | C11: Limpieza | D11: Hogar Plus | E11: 20 | F11: 5.2 | G11: 8.5 | H11: =IF(B11="","",G11-F11) -> 3.3 | I11: =IF(OR(B11="",G11=0),"",H11/G11) -> 0.38823529 | J11: 6
A12: P008 | B12: Papel higiénico (12 rollos) | C12: Limpieza | D12: Hogar Plus | E12: 25 | F12: 3.4 | G12: 5.6 | H12: =IF(B12="","",G12-F12) -> 2.2 | I12: =IF(OR(B12="",G12=0),"",H12/G12) -> 0.39285714 | J12: 8
A13: P009 | B13: Galletas surtidas | C13: Snacks | D13: Dulces SA | E13: 35 | F13: 1.2 | G13: 2.2 | H13: =IF(B13="","",G13-F13) -> 1 | I13: =IF(OR(B13="",G13=0),"",H13/G13) -> 0.45454545 | J13: 10
A14: P010 | B14: Patatas fritas 150 g | C14: Snacks | D14: Dulces SA | E14: 40 | F14: 0.95 | G14: 1.8 | H14: =IF(B14="","",G14-F14) -> 0.85 | I14: =IF(OR(B14="",G14=0),"",H14/G14) -> 0.47222222 | J14: 12
A15: P011 | B15: Cuaderno A4 | C15: Papelería | D15: Papelería Express | E15: 15 | F15: 1.4 | G15: 2.9 | H15: =IF(B15="","",G15-F15) -> 1.5 | I15: =IF(OR(B15="",G15=0),"",H15/G15) -> 0.51724138 | J15: 5
A16: P012 | B16: Bolígrafos (pack 10) | C16: Papelería | D16: Papelería Express | E16: 12 | F16: 2.1 | G16: 4.2 | H16: =IF(B16="","",G16-F16) -> 2.1 | I16: =IF(OR(B16="",G16=0),"",H16/G16) -> 0.5 | J16: 4
H17: =IF(B17="","",G17-F17) | I17: =IF(OR(B17="",G17=0),"",H17/G17)
H18: =IF(B18="","",G18-F18) | I18: =IF(OR(B18="",G18=0),"",H18/G18)
H19: =IF(B19="","",G19-F19) | I19: =IF(OR(B19="",G19=0),"",H19/G19)
H20: =IF(B20="","",G20-F20) | I20: =IF(OR(B20="",G20=0),"",H20/G20)
H21: =IF(B21="","",G21-F21) | I21: =IF(OR(B21="",G21=0),"",H21/G21)
H22: =IF(B22="","",G22-F22) | I22: =IF(OR(B22="",G22=0),"",H22/G22)
H23: =IF(B23="","",G23-F23) | I23: =IF(OR(B23="",G23=0),"",H23/G23)
H24: =IF(B24="","",G24-F24) | I24: =IF(OR(B24="",G24=0),"",H24/G24)
H25: =IF(B25="","",G25-F25) | I25: =IF(OR(B25="",G25=0),"",H25/G25)
H26: =IF(B26="","",G26-F26) | I26: =IF(OR(B26="",G26=0),"",H26/G26)
H27: =IF(B27="","",G27-F27) | I27: =IF(OR(B27="",G27=0),"",H27/G27)
H28: =IF(B28="","",G28-F28) | I28: =IF(OR(B28="",G28=0),"",H28/G28)
... H104: =IF(B104="","",G104-F104) | I104: =IF(OR(B104="",G104=0),"",H104/G104)

Sheet Inventario
A1: Inventario
A2: Todo se calcula solo: Cantidad actual en el almacén = Cantidad inicial + Entradas (Compras) − Salidas (Ventas).
A3: TOTALES | D3: =SUM(D5:D104) -> 452 | E3: =SUM(E5:E104) -> 277 | F3: =SUM(F5:F104) -> 124 | G3: =SUM(G5:G104) -> 605 | I3: =COUNTIF(I5:I104,"REPONER")+COUNTIF(I5:I104,"AGOTADO")&" a reponer" -> 1 a reponer | K3: =SUM(K5:K104) -> 814.15 | L3: =SUM(L5:L104) -> 1377.9
A4: Código | B4: Producto | C4: Categoría | D4: Cantidad inicial en el almacén | E4: Entradas | F4: Salidas | G4: Cantidad actual en el almacén | H4: Cantidad mínima en el almacén | I4: Estado | J4: Costo unitario | K4: Valor inventario (costo) | L4: Valor inventario (venta)
A5: =IF(Productos!B5="","",Productos!A5) -> P001 | B5: =IF(Productos!B5="","",Productos!B5) -> Arroz 1 kg | C5: =IF(B5="","",Productos!C5) -> Alimentos | D5: =IF(B5="","",N(Productos!E5)) -> 50 | E5: =IF(B5="","",SUMIFS(Compras!$E$5:$E$304,Compras!$B$5:$B$304,B5)) -> 40 | F5: =IF(B5="","",SUMIFS(Ventas!$F$5:$F$504,Ventas!$C$5:$C$504,B5)) -> 13 | G5: =IF(B5="","",D5+E5-F5) -> 77 | H5: =IF(B5="","",N(Productos!J5)) -> 15 | I5: =IF(B5="","",IF(G5<=0,"AGOTADO",IF(G5<=H5,"REPONER","OK"))) -> OK | J5: =IF(B5="","",N(Productos!F5)) -> 0.9 | K5: =IF(B5="","",G5*J5) -> 69.3 | L5: =IF(B5="","",G5*N(Productos!G5)) -> 115.5
A6: =IF(Productos!B6="","",Productos!A6) -> P002 | B6: =IF(Productos!B6="","",Productos!B6) -> Aceite de oliva 1 L | C6: =IF(B6="","",Productos!C6) -> Alimentos | D6: =IF(B6="","",N(Productos!E6)) -> 30 | E6: =IF(B6="","",SUMIFS(Compras!$E$5:$E$304,Compras!$B$5:$B$304,B6)) -> 20 | F6: =IF(B6="","",SUMIFS(Ventas!$F$5:$F$504,Ventas!$C$5:$C$504,B6)) -> 5 | G6: =IF(B6="","",D6+E6-F6) -> 45 | H6: =IF(B6="","",N(Productos!J6)) -> 10 | I6: =IF(B6="","",IF(G6<=0,"AGOTADO",IF(G6<=H6,"REPONER","OK"))) -> OK | J6: =IF(B6="","",N(Productos!F6)) -> 4.5 | K6: =IF(B6="","",G6*J6) -> 202.5 | L6: =IF(B6="","",G6*N(Productos!G6)) -> 310.5
A7: =IF(Productos!B7="","",Productos!A7) -> P003 | B7: =IF(Productos!B7="","",Productos!B7) -> Leche entera 1 L | C7: =IF(B7="","",Productos!C7) -> Lácteos | D7: =IF(B7="","",N(Productos!E7)) -> 60 | E7: =IF(B7="","",SUMIFS(Compras!$E$5:$E$304,Compras!$B$5:$B$304,B7)) -> 60 | F7: =IF(B7="","",SUMIFS(Ventas!$F$5:$F$504,Ventas!$C$5:$C$504,B7)) -> 31 | G7: =IF(B7="","",D7+E7-F7) -> 89 | H7: =IF(B7="","",N(Productos!J7)) -> 20 | I7: =IF(B7="","",IF(G7<=0,"AGOTADO",IF(G7<=H7,"REPONER","OK"))) -> OK | J7: =IF(B7="","",N(Productos!F7)) -> 0.65 | K7: =IF(B7="","",G7*J7) -> 57.85 | L7: =IF(B7="","",G7*N(Productos!G7)) -> 93.45
A8: =IF(Productos!B8="","",Productos!A8) -> P004 | B8: =IF(Productos!B8="","",Productos!B8) -> Yogur natural (pack 4) | C8: =IF(B8="","",Productos!C8) -> Lácteos | D8: =IF(B8="","",N(Productos!E8)) -> 40 | E8: =IF(B8="","",SUMIFS(Compras!$E$5:$E$304,Compras!$B$5:$B$304,B8)) -> 0 | F8: =IF(B8="","",SUMIFS(Ventas!$F$5:$F$504,Ventas!$C$5:$C$504,B8)) -> 8 | G8: =IF(B8="","",D8+E8-F8) -> 32 | H8: =IF(B8="","",N(Productos!J8)) -> 12 | I8: =IF(B8="","",IF(G8<=0,"AGOTADO",IF(G8<=H8,"REPONER","OK"))) -> OK | J8: =IF(B8="","",N(Productos!F8)) -> 1.1 | K8: =IF(B8="","",G8*J8) -> 35.2 | L8: =IF(B8="","",G8*N(Productos!G8)) -> 59.2
A9: =IF(Productos!B9="","",Productos!A9) -> P005 | B9: =IF(Productos!B9="","",Productos!B9) -> Refresco cola 2 L | C9: =IF(B9="","",Productos!C9) -> Bebidas | D9: =IF(B9="","",N(Productos!E9)) -> 45 | E9: =IF(B9="","",SUMIFS(Compras!$E$5:$E$304,Compras!$B$5:$B$304,B9)) -> 30 | F9: =IF(B9="","",SUMIFS(Ventas!$F$5:$F$504,Ventas!$C$5:$C$504,B9)) -> 16 | G9: =IF(B9="","",D9+E9-F9) -> 59 | H9: =IF(B9="","",N(Productos!J9)) -> 15 | I9: =IF(B9="","",IF(G9<=0,"AGOTADO",IF(G9<=H9,"REPONER","OK"))) -> OK | J9: =IF(B9="","",N(Productos!F9)) -> 1 | K9: =IF(B9="","",G9*J9) -> 59 | L9: =IF(B9="","",G9*N(Productos!G9)) -> 103.25
A10: =IF(Productos!B10="","",Productos!A10) -> P006 | B10: =IF(Productos!B10="","",Productos!B10) -> Agua mineral 1,5 L | C10: =IF(B10="","",Productos!C10) -> Bebidas | D10: =IF(B10="","",N(Productos!E10)) -> 80 | E10: =IF(B10="","",SUMIFS(Compras!$E$5:$E$304,Compras!$B$5:$B$304,B10)) -> 60 | F10: =IF(B10="","",SUMIFS(Ventas!$F$5:$F$504,Ventas!$C$5:$C$504,B10)) -> 12 | G10: =IF(B10="","",D10+E10-F10) -> 128 | H10: =IF(B10="","",N(Productos!J10)) -> 30 | I10: =IF(B10="","",IF(G10<=0,"AGOTADO",IF(G10<=H10,"REPONER","OK"))) -> OK | J10: =IF(B10="","",N(Productos!F10)) -> 0.3 | K10: =IF(B10="","",G10*J10) -> 38.4 | L10: =IF(B10="","",G10*N(Productos!G10)) -> 83.2
A11: =IF(Productos!B11="","",Productos!A11) -> P007 | B11: =IF(Productos!B11="","",Productos!B11) -> Detergente 3 L | C11: =IF(B11="","",Productos!C11) -> Limpieza | D11: =IF(B11="","",N(Productos!E11)) -> 20 | E11: =IF(B11="","",SUMIFS(Compras!$E$5:$E$304,Compras!$B$5:$B$304,B11)) -> 12 | F11: =IF(B11="","",SUMIFS(Ventas!$F$5:$F$504,Ventas!$C$5:$C$504,B11)) -> 5 | G11: =IF(B11="","",D11+E11-F11) -> 27 | H11: =IF(B11="","",N(Productos!J11)) -> 6 | I11: =IF(B11="","",IF(G11<=0,"AGOTADO",IF(G11<=H11,"REPONER","OK"))) -> OK | J11: =IF(B11="","",N(Productos!F11)) -> 5.2 | K11: =IF(B11="","",G11*J11) -> 140.4 | L11: =IF(B11="","",G11*N(Productos!G11)) -> 229.5
A12: =IF(Productos!B12="","",Productos!A12) -> P008 | B12: =IF(Productos!B12="","",Productos!B12) -> Papel higiénico (12 rollos) | C12: =IF(B12="","",Productos!C12) -> Limpieza | D12: =IF(B12="","",N(Productos!E12)) -> 25 | E12: =IF(B12="","",SUMIFS(Compras!$E$5:$E$304,Compras!$B$5:$B$304,B12)) -> 0 | F12: =IF(B12="","",SUMIFS(Ventas!$F$5:$F$504,Ventas!$C$5:$C$504,B12)) -> 5 | G12: =IF(B12="","",D12+E12-F12) -> 20 | H12: =IF(B12="","",N(Productos!J12)) -> 8 | I12: =IF(B12="","",IF(G12<=0,"AGOTADO",IF(G12<=H12,"REPONER","OK"))) -> OK | J12: =IF(B12="","",N(Productos!F12)) -> 3.4 | K12: =IF(B12="","",G12*J12) -> 68 | L12: =IF(B12="","",G12*N(Productos!G12)) -> 112
A13: =IF(Productos!B13="","",Productos!A13) -> P009 | B13: =IF(Productos!B13="","",Productos!B13) -> Galletas surtidas | C13: =IF(B13="","",Productos!C13) -> Snacks | D13: =IF(B13="","",N(Productos!E13)) -> 35 | E13: =IF(B13="","",SUMIFS(Compras!$E$5:$E$304,Compras!$B$5:$B$304,B13)) -> 25 | F13: =IF(B13="","",SUMIFS(Ventas!$F$5:$F$504,Ventas!$C$5:$C$504,B13)) -> 6 | G13: =IF(B13="","",D13+E13-F13) -> 54 | H13: =IF(B13="","",N(Productos!J13)) -> 10 | I13: =IF(B13="","",IF(G13<=0,"AGOTADO",IF(G13<=H13,"REPONER","OK"))) -> OK | J13: =IF(B13="","",N(Productos!F13)) -> 1.2 | K13: =IF(B13="","",G13*J13) -> 64.8 | L13: =IF(B13="","",G13*N(Productos!G13)) -> 118.8
A14: =IF(Productos!B14="","",Productos!A14) -> P010 | B14: =IF(Productos!B14="","",Productos!B14) -> Patatas fritas 150 g | C14: =IF(B14="","",Productos!C14) -> Snacks | D14: =IF(B14="","",N(Productos!E14)) -> 40 | E14: =IF(B14="","",SUMIFS(Compras!$E$5:$E$304,Compras!$B$5:$B$304,B14)) -> 30 | F14: =IF(B14="","",SUMIFS(Ventas!$F$5:$F$504,Ventas!$C$5:$C$504,B14)) -> 10 | G14: =IF(B14="","",D14+E14-F14) -> 60 | H14: =IF(B14="","",N(Productos!J14)) -> 12 | I14: =IF(B14="","",IF(G14<=0,"AGOTADO",IF(G14<=H14,"REPONER","OK"))) -> OK | J14: =IF(B14="","",N(Productos!F14)) -> 0.95 | K14: =IF(B14="","",G14*J14) -> 57 | L14: =IF(B14="","",G14*N(Productos!G14)) -> 108
A15: =IF(Productos!B15="","",Productos!A15) -> P011 | B15: =IF(Productos!B15="","",Productos!B15) -> Cuaderno A4 | C15: =IF(B15="","",Productos!C15) -> Papelería | D15: =IF(B15="","",N(Productos!E15)) -> 15 | E15: =IF(B15="","",SUMIFS(Compras!$E$5:$E$304,Compras!$B$5:$B$304,B15)) -> 0 | F15: =IF(B15="","",SUMIFS(Ventas!$F$5:$F$504,Ventas!$C$5:$C$504,B15)) -> 4 | G15: =IF(B15="","",D15+E15-F15) -> 11 | H15: =IF(B15="","",N(Productos!J15)) -> 5 | I15: =IF(B15="","",IF(G15<=0,"AGOTADO",IF(G15<=H15,"REPONER","OK"))) -> OK | J15: =IF(B15="","",N(Productos!F15)) -> 1.4 | K15: =IF(B15="","",G15*J15) -> 15.4 | L15: =IF(B15="","",G15*N(Productos!G15)) -> 31.9
A16: =IF(Productos!B16="","",Productos!A16) -> P012 | B16: =IF(Productos!B16="","",Productos!B16) -> Bolígrafos (pack 10) | C16: =IF(B16="","",Productos!C16) -> Papelería | D16: =IF(B16="","",N(Productos!E16)) -> 12 | E16: =IF(B16="","",SUMIFS(Compras!$E$5:$E$304,Compras!$B$5:$B$304,B16)) -> 0 | F16: =IF(B16="","",SUMIFS(Ventas!$F$5:$F$504,Ventas!$C$5:$C$504,B16)) -> 9 | G16: =IF(B16="","",D16+E16-F16) -> 3 | H16: =IF(B16="","",N(Productos!J16)) -> 4 | I16: =IF(B16="","",IF(G16<=0,"AGOTADO",IF(G16<=H16,"REPONER","OK"))) -> REPONER | J16: =IF(B16="","",N(Productos!F16)) -> 2.1 | K16: =IF(B16="","",G16*J16) -> 6.3 | L16: =IF(B16="","",G16*N(Productos!G16)) -> 12.6
... A104: =IF(Productos!B104="","",Productos!A104) | B104: =IF(Productos!B104="","",Productos!B104) | C104: =IF(B104="","",Productos!C104) | D104: =IF(B104="","",N(Productos!E104)) | E104: =IF(B104="","",SUMIFS(Compras!$E$5:$E$304,Compras!$B$5:$B$304,B104)) | F104: =IF(B104="","",SUMIFS(Ventas!$F$5:$F$504,Ventas!$C$5:$C$504,B104)) | G104: =IF(B104="","",D104+E104-F104) | H104: =IF(B104="","",N(Productos!J104)) | I104: =IF(B104="","",IF(G104<=0,"AGOTADO",IF(G104<=H104,"REPONER","OK"))) | J104: =IF(B104="","",N(Productos!F104)) | K104: =IF(B104="","",G104*J104) | L104: =IF(B104="","",G104*N(Productos!G104))

Sheet Ventas
A1: Ventas / Salidas
A2: Elige el Producto en la lista y escribe Fecha, N° de venta, Cantidad, Descuento y Método de pago (azul); el resto se completa solo.
A3: TOTALES | F3: =SUM(F5:F504) -> 124 | I3: =SUM(I5:I504) -> 285.06 | L3: =SUM(L5:L504) -> 166.95 | M3: =SUM(M5:M504) -> 118.11
A4: Fecha | B4: N° venta | C4: Producto | D4: Código | E4: Categoría | F4: Cantidad | G4: Precio unitario | H4: Descuento % | I4: Total venta | J4: Método de pago | K4: Cliente (opcional) | L4: Costo | M4: Ganancia
A5: 46268 | B5: 1001 | C5: Arroz 1 kg | D5: =IF(C5="","",IFERROR(INDEX(Productos!$A$5:$A$104,MATCH(C5,Productos!$B$5:$B$104,0)),"")) -> P001 | E5: =IF(C5="","",IFERROR(INDEX(Productos!$C$5:$C$104,MATCH(C5,Productos!$B$5:$B$104,0)),"")) -> Alimentos | F5: 3 | G5: =IF(C5="","",IFERROR(INDEX(Productos!$G$5:$G$104,MATCH(C5,Productos!$B$5:$B$104,0)),0)) -> 1.5 | H5: 0 | I5: =IF(C5="","",F5*G5*(1-H5)) -> 4.5 | J5: Efectivo | L5: =IF(C5="","",F5*IFERROR(INDEX(Productos!$F$5:$F$104,MATCH(C5,Productos!$B$5:$B$104,0)),0)) -> 2.7 | M5: =IF(C5="","",I5-L5) -> 1.8
A6: 46268 | B6: 1001 | C6: Leche entera 1 L | D6: =IF(C6="","",IFERROR(INDEX(Productos!$A$5:$A$104,MATCH(C6,Productos!$B$5:$B$104,0)),"")) -> P003 | E6: =IF(C6="","",IFERROR(INDEX(Productos!$C$5:$C$104,MATCH(C6,Productos!$B$5:$B$104,0)),"")) -> Lácteos | F6: 6 | G6: =IF(C6="","",IFERROR(INDEX(Productos!$G$5:$G$104,MATCH(C6,Productos!$B$5:$B$104,0)),0)) -> 1.05 | H6: 0 | I6: =IF(C6="","",F6*G6*(1-H6)) -> 6.3 | J6: Efectivo | L6: =IF(C6="","",F6*IFERROR(INDEX(Productos!$F$5:$F$104,MATCH(C6,Productos!$B$5:$B$104,0)),0)) -> 3.9 | M6: =IF(C6="","",I6-L6) -> 2.4
A7: 46270 | B7: 1002 | C7: Refresco cola 2 L | D7: =IF(C7="","",IFERROR(INDEX(Productos!$A$5:$A$104,MATCH(C7,Productos!$B$5:$B$104,0)),"")) -> P005 | E7: =IF(C7="","",IFERROR(INDEX(Productos!$C$5:$C$104,MATCH(C7,Productos!$B$5:$B$104,0)),"")) -> Bebidas | F7: 4 | G7: =IF(C7="","",IFERROR(INDEX(Productos!$G$5:$G$104,MATCH(C7,Productos!$B$5:$B$104,0)),0)) -> 1.75 | H7: 0 | I7: =IF(C7="","",F7*G7*(1-H7)) -> 7 | J7: Transferencia | K7: María López | L7: =IF(C7="","",F7*IFERROR(INDEX(Productos!$F$5:$F$104,MATCH(C7,Productos!$B$5:$B$104,0)),0)) -> 4 | M7: =IF(C7="","",I7-L7) -> 3
A8: 46273 | B8: 1003 | C8: Agua mineral 1,5 L | D8: =IF(C8="","",IFERROR(INDEX(Productos!$A$5:$A$104,MATCH(C8,Productos!$B$5:$B$104,0)),"")) -> P006 | E8: =IF(C8="","",IFERROR(INDEX(Productos!$C$5:$C$104,MATCH(C8,Productos!$B$5:$B$104,0)),"")) -> Bebidas | F8: 12 | G8: =IF(C8="","",IFERROR(INDEX(Productos!$G$5:$G$104,MATCH(C8,Productos!$B$5:$B$104,0)),0)) -> 0.65 | H8: 0.05 | I8: =IF(C8="","",F8*G8*(1-H8)) -> 7.41 | J8: Transferencia | L8: =IF(C8="","",F8*IFERROR(INDEX(Productos!$F$5:$F$104,MATCH(C8,Productos!$B$5:$B$104,0)),0)) -> 3.6 | M8: =IF(C8="","",I8-L8) -> 3.81
A9: 46277 | B9: 1004 | C9: Detergente 3 L | D9: =IF(C9="","",IFERROR(INDEX(Productos!$A$5:$A$104,MATCH(C9,Productos!$B$5:$B$104,0)),"")) -> P007 | E9: =IF(C9="","",IFERROR(INDEX(Productos!$C$5:$C$104,MATCH(C9,Productos!$B$5:$B$104,0)),"")) -> Limpieza | F9: 2 | G9: =IF(C9="","",IFERROR(INDEX(Productos!$G$5:$G$104,MATCH(C9,Productos!$B$5:$B$104,0)),0)) -> 8.5 | H9: 0 | I9: =IF(C9="","",F9*G9*(1-H9)) -> 17 | J9: Transferencia | K9: Bar El Sol | L9: =IF(C9="","",F9*IFERROR(INDEX(Productos!$F$5:$F$104,MATCH(C9,Productos!$B$5:$B$104,0)),0)) -> 10.4 | M9: =IF(C9="","",I9-L9) -> 6.6
A10: 46281 | B10: 1005 | C10: Galletas surtidas | D10: =IF(C10="","",IFERROR(INDEX(Productos!$A$5:$A$104,MATCH(C10,Productos!$B$5:$B$104,0)),"")) -> P009 | E10: =IF(C10="","",IFERROR(INDEX(Productos!$C$5:$C$104,MATCH(C10,Productos!$B$5:$B$104,0)),"")) -> Snacks | F10: 6 | G10: =IF(C10="","",IFERROR(INDEX(Productos!$G$5:$G$104,MATCH(C10,Productos!$B$5:$B$104,0)),0)) -> 2.2 | H10: 0 | I10: =IF(C10="","",F10*G10*(1-H10)) -> 13.2 | J10: Efectivo | L10: =IF(C10="","",F10*IFERROR(INDEX(Productos!$F$5:$F$104,MATCH(C10,Productos!$B$5:$B$104,0)),0)) -> 7.2 | M10: =IF(C10="","",I10-L10) -> 6
A11: 46284 | B11: 1006 | C11: Aceite de oliva 1 L | D11: =IF(C11="","",IFERROR(INDEX(Productos!$A$5:$A$104,MATCH(C11,Productos!$B$5:$B$104,0)),"")) -> P002 | E11: =IF(C11="","",IFERROR(INDEX(Productos!$C$5:$C$104,MATCH(C11,Productos!$B$5:$B$104,0)),"")) -> Alimentos | F11: 5 | G11: =IF(C11="","",IFERROR(INDEX(Productos!$G$5:$G$104,MATCH(C11,Productos!$B$5:$B$104,0)),0)) -> 6.9 | H11: 0 | I11: =IF(C11="","",F11*G11*(1-H11)) -> 34.5 | J11: Efectivo | L11: =IF(C11="","",F11*IFERROR(INDEX(Productos!$F$5:$F$104,MATCH(C11,Productos!$B$5:$B$104,0)),0)) -> 22.5 | M11: =IF(C11="","",I11-L11) -> 12
A12: 46289 | B12: 1007 | C12: Patatas fritas 150 g | D12: =IF(C12="","",IFERROR(INDEX(Productos!$A$5:$A$104,MATCH(C12,Productos!$B$5:$B$104,0)),"")) -> P010 | E12: =IF(C12="","",IFERROR(INDEX(Productos!$C$5:$C$104,MATCH(C12,Productos!$B$5:$B$104,0)),"")) -> Snacks | F12: 10 | G12: =IF(C12="","",IFERROR(INDEX(Productos!$G$5:$G$104,MATCH(C12,Productos!$B$5:$B$104,0)),0)) -> 1.8 | H12: 0 | I12: =IF(C12="","",F12*G12*(1-H12)) -> 18 | J12: Efectivo | L12: =IF(C12="","",F12*IFERROR(INDEX(Productos!$F$5:$F$104,MATCH(C12,Productos!$B$5:$B$104,0)),0)) -> 9.5 | M12: =IF(C12="","",I12-L12) -> 8.5
A13: 46292 | B13: 1008 | C13: Cuaderno A4 | D13: =IF(C13="","",IFERROR(INDEX(Productos!$A$5:$A$104,MATCH(C13,Productos!$B$5:$B$104,0)),"")) -> P011 | E13: =IF(C13="","",IFERROR(INDEX(Productos!$C$5:$C$104,MATCH(C13,Productos!$B$5:$B$104,0)),"")) -> Papelería | F13: 4 | G13: =IF(C13="","",IFERROR(INDEX(Productos!$G$5:$G$104,MATCH(C13,Productos!$B$5:$B$104,0)),0)) -> 2.9 | H13: 0 | I13: =IF(C13="","",F13*G13*(1-H13)) -> 11.6 | J13: Transferencia | K13: Colegio San Juan | L13: =IF(C13="","",F13*IFERROR(INDEX(Productos!$F$5:$F$104,MATCH(C13,Productos!$B$5:$B$104,0)),0)) -> 5.6 | M13: =IF(C13="","",I13-L13) -> 6
A14: 46297 | B14: 1009 | C14: Yogur natural (pack 4) | D14: =IF(C14="","",IFERROR(INDEX(Productos!$A$5:$A$104,MATCH(C14,Productos!$B$5:$B$104,0)),"")) -> P004 | E14: =IF(C14="","",IFERROR(INDEX(Productos!$C$5:$C$104,MATCH(C14,Productos!$B$5:$B$104,0)),"")) -> Lácteos | F14: 8 | G14: =IF(C14="","",IFERROR(INDEX(Productos!$G$5:$G$104,MATCH(C14,Productos!$B$5:$B$104,0)),0)) -> 1.85 | H14: 0 | I14: =IF(C14="","",F14*G14*(1-H14)) -> 14.8 | J14: Efectivo | L14: =IF(C14="","",F14*IFERROR(INDEX(Productos!$F$5:$F$104,MATCH(C14,Productos!$B$5:$B$104,0)),0)) -> 8.8 | M14: =IF(C14="","",I14-L14) -> 6
A15: 46299 | B15: 1010 | C15: Papel higiénico (12 rollos) | D15: =IF(C15="","",IFERROR(INDEX(Productos!$A$5:$A$104,MATCH(C15,Productos!$B$5:$B$104,0)),"")) -> P008 | E15: =IF(C15="","",IFERROR(INDEX(Productos!$C$5:$C$104,MATCH(C15,Productos!$B$5:$B$104,0)),"")) -> Limpieza | F15: 5 | G15: =IF(C15="","",IFERROR(INDEX(Productos!$G$5:$G$104,MATCH(C15,Productos!$B$5:$B$104,0)),0)) -> 5.6 | H15: 0.1 | I15: =IF(C15="","",F15*G15*(1-H15)) -> 25.2 | J15: Transferencia | K15: Bar El Sol | L15: =IF(C15="","",F15*IFERROR(INDEX(Productos!$F$5:$F$104,MATCH(C15,Productos!$B$5:$B$104,0)),0)) -> 17 | M15: =IF(C15="","",I15-L15) -> 8.2
A16: 46302 | B16: 1011 | C16: Bolígrafos (pack 10) | D16: =IF(C16="","",IFERROR(INDEX(Productos!$A$5:$A$104,MATCH(C16,Productos!$B$5:$B$104,0)),"")) -> P012 | E16: =IF(C16="","",IFERROR(INDEX(Productos!$C$5:$C$104,MATCH(C16,Productos!$B$5:$B$104,0)),"")) -> Papelería | F16: 9 | G16: =IF(C16="","",IFERROR(INDEX(Productos!$G$5:$G$104,MATCH(C16,Productos!$B$5:$B$104,0)),0)) -> 4.2 | H16: 0 | I16: =IF(C16="","",F16*G16*(1-H16)) -> 37.8 | J16: Transferencia | K16: Colegio San Juan | L16: =IF(C16="","",F16*IFERROR(INDEX(Productos!$F$5:$F$104,MATCH(C16,Productos!$B$5:$B$104,0)),0)) -> 18.9 | M16: =IF(C16="","",I16-L16) -> 18.9
A17: 46305 | B17: 1012 | C17: Refresco cola 2 L | D17: =IF(C17="","",IFERROR(INDEX(Productos!$A$5:$A$104,MATCH(C17,Productos!$B$5:$B$104,0)),"")) -> P005 | E17: =IF(C17="","",IFERROR(INDEX(Productos!$C$5:$C$104,MATCH(C17,Productos!$B$5:$B$104,0)),"")) -> Bebidas | F17: 12 | G17: =IF(C17="","",IFERROR(INDEX(Productos!$G$5:$G$104,MATCH(C17,Productos!$B$5:$B$104,0)),0)) -> 1.75 | H17: 0 | I17: =IF(C17="","",F17*G17*(1-H17)) -> 21 | J17: Efectivo | L17: =IF(C17="","",F17*IFERROR(INDEX(Productos!$F$5:$F$104,MATCH(C17,Productos!$B$5:$B$104,0)),0)) -> 12 | M17: =IF(C17="","",I17-L17) -> 9
A18: 46308 | B18: 1013 | C18: Leche entera 1 L | D18: =IF(C18="","",IFERROR(INDEX(Productos!$A$5:$A$104,MATCH(C18,Productos!$B$5:$B$104,0)),"")) -> P003 | E18: =IF(C18="","",IFERROR(INDEX(Productos!$C$5:$C$104,MATCH(C18,Productos!$B$5:$B$104,0)),"")) -> Lácteos | F18: 25 | G18: =IF(C18="","",IFERROR(INDEX(Productos!$G$5:$G$104,MATCH(C18,Productos!$B$5:$B$104,0)),0)) -> 1.05 | H18: 0 | I18: =IF(C18="","",F18*G18*(1-H18)) -> 26.25 | J18: Transferencia | L18: =IF(C18="","",F18*IFERROR(INDEX(Productos!$F$5:$F$104,MATCH(C18,Productos!$B$5:$B$104,0)),0)) -> 16.25 | M18: =IF(C18="","",I18-L18) -> 10
A19: 46312 | B19: 1014 | C19: Arroz 1 kg | D19: =IF(C19="","",IFERROR(INDEX(Productos!$A$5:$A$104,MATCH(C19,Productos!$B$5:$B$104,0)),"")) -> P001 | E19: =IF(C19="","",IFERROR(INDEX(Productos!$C$5:$C$104,MATCH(C19,Productos!$B$5:$B$104,0)),"")) -> Alimentos | F19: 10 | G19: =IF(C19="","",IFERROR(INDEX(Productos!$G$5:$G$104,MATCH(C19,Productos!$B$5:$B$104,0)),0)) -> 1.5 | H19: 0 | I19: =IF(C19="","",F19*G19*(1-H19)) -> 15 | J19: Efectivo | L19: =IF(C19="","",F19*IFERROR(INDEX(Productos!$F$5:$F$104,MATCH(C19,Productos!$B$5:$B$104,0)),0)) -> 9 | M19: =IF(C19="","",I19-L19) -> 6
A20: 46315 | B20: 1015 | C20: Detergente 3 L | D20: =IF(C20="","",IFERROR(INDEX(Productos!$A$5:$A$104,MATCH(C20,Productos!$B$5:$B$104,0)),"")) -> P007 | E20: =IF(C20="","",IFERROR(INDEX(Productos!$C$5:$C$104,MATCH(C20,Productos!$B$5:$B$104,0)),"")) -> Limpieza | F20: 3 | G20: =IF(C20="","",IFERROR(INDEX(Productos!$G$5:$G$104,MATCH(C20,Productos!$B$5:$B$104,0)),0)) -> 8.5 | H20: 0 | I20: =IF(C20="","",F20*G20*(1-H20)) -> 25.5 | J20: Efectivo | L20: =IF(C20="","",F20*IFERROR(INDEX(Productos!$F$5:$F$104,MATCH(C20,Productos!$B$5:$B$104,0)),0)) -> 15.6 | M20: =IF(C20="","",I20-L20) -> 9.9
D21: =IF(C21="","",IFERROR(INDEX(Productos!$A$5:$A$104,MATCH(C21,Productos!$B$5:$B$104,0)),"")) | E21: =IF(C21="","",IFERROR(INDEX(Productos!$C$5:$C$104,MATCH(C21,Productos!$B$5:$B$104,0)),"")) | G21: =IF(C21="","",IFERROR(INDEX(Productos!$G$5:$G$104,MATCH(C21,Productos!$B$5:$B$104,0)),0)) | I21: =IF(C21="","",F21*G21*(1-H21)) | L21: =IF(C21="","",F21*IFERROR(INDEX(Productos!$F$5:$F$104,MATCH(C21,Productos!$B$5:$B$104,0)),0)) | M21: =IF(C21="","",I21-L21)
D22: =IF(C22="","",IFERROR(INDEX(Productos!$A$5:$A$104,MATCH(C22,Productos!$B$5:$B$104,0)),"")) | E22: =IF(C22="","",IFERROR(INDEX(Productos!$C$5:$C$104,MATCH(C22,Productos!$B$5:$B$104,0)),"")) | G22: =IF(C22="","",IFERROR(INDEX(Productos!$G$5:$G$104,MATCH(C22,Productos!$B$5:$B$104,0)),0)) | I22: =IF(C22="","",F22*G22*(1-H22)) | L22: =IF(C22="","",F22*IFERROR(INDEX(Productos!$F$5:$F$104,MATCH(C22,Productos!$B$5:$B$104,0)),0)) | M22: =IF(C22="","",I22-L22)
D23: =IF(C23="","",IFERROR(INDEX(Productos!$A$5:$A$104,MATCH(C23,Productos!$B$5:$B$104,0)),"")) | E23: =IF(C23="","",IFERROR(INDEX(Productos!$C$5:$C$104,MATCH(C23,Productos!$B$5:$B$104,0)),"")) | G23: =IF(C23="","",IFERROR(INDEX(Productos!$G$5:$G$104,MATCH(C23,Productos!$B$5:$B$104,0)),0)) | I23: =IF(C23="","",F23*G23*(1-H23)) | L23: =IF(C23="","",F23*IFERROR(INDEX(Productos!$F$5:$F$104,MATCH(C23,Productos!$B$5:$B$104,0)),0)) | M23: =IF(C23="","",I23-L23)
D24: =IF(C24="","",IFERROR(INDEX(Productos!$A$5:$A$104,MATCH(C24,Productos!$B$5:$B$104,0)),"")) | E24: =IF(C24="","",IFERROR(INDEX(Productos!$C$5:$C$104,MATCH(C24,Productos!$B$5:$B$104,0)),"")) | G24: =IF(C24="","",IFERROR(INDEX(Productos!$G$5:$G$104,MATCH(C24,Productos!$B$5:$B$104,0)),0)) | I24: =IF(C24="","",F24*G24*(1-H24)) | L24: =IF(C24="","",F24*IFERROR(INDEX(Productos!$F$5:$F$104,MATCH(C24,Productos!$B$5:$B$104,0)),0)) | M24: =IF(C24="","",I24-L24)
D25: =IF(C25="","",IFERROR(INDEX(Productos!$A$5:$A$104,MATCH(C25,Productos!$B$5:$B$104,0)),"")) | E25: =IF(C25="","",IFERROR(INDEX(Productos!$C$5:$C$104,MATCH(C25,Productos!$B$5:$B$104,0)),"")) | G25: =IF(C25="","",IFERROR(INDEX(Productos!$G$5:$G$104,MATCH(C25,Productos!$B$5:$B$104,0)),0)) | I25: =IF(C25="","",F25*G25*(1-H25)) | L25: =IF(C25="","",F25*IFERROR(INDEX(Productos!$F$5:$F$104,MATCH(C25,Productos!$B$5:$B$104,0)),0)) | M25: =IF(C25="","",I25-L25)
D26: =IF(C26="","",IFERROR(INDEX(Productos!$A$5:$A$104,MATCH(C26,Productos!$B$5:$B$104,0)),"")) | E26: =IF(C26="","",IFERROR(INDEX(Productos!$C$5:$C$104,MATCH(C26,Productos!$B$5:$B$104,0)),"")) | G26: =IF(C26="","",IFERROR(INDEX(Productos!$G$5:$G$104,MATCH(C26,Productos!$B$5:$B$104,0)),0)) | I26: =IF(C26="","",F26*G26*(1-H26)) | L26: =IF(C26="","",F26*IFERROR(INDEX(Productos!$F$5:$F$104,MATCH(C26,Productos!$B$5:$B$104,0)),0)) | M26: =IF(C26="","",I26-L26)
D27: =IF(C27="","",IFERROR(INDEX(Productos!$A$5:$A$104,MATCH(C27,Productos!$B$5:$B$104,0)),"")) | E27: =IF(C27="","",IFERROR(INDEX(Productos!$C$5:$C$104,MATCH(C27,Productos!$B$5:$B$104,0)),"")) | G27: =IF(C27="","",IFERROR(INDEX(Productos!$G$5:$G$104,MATCH(C27,Productos!$B$5:$B$104,0)),0)) | I27: =IF(C27="","",F27*G27*(1-H27)) | L27: =IF(C27="","",F27*IFERROR(INDEX(Productos!$F$5:$F$104,MATCH(C27,Productos!$B$5:$B$104,0)),0)) | M27: =IF(C27="","",I27-L27)
D28: =IF(C28="","",IFERROR(INDEX(Productos!$A$5:$A$104,MATCH(C28,Productos!$B$5:$B$104,0)),"")) | E28: =IF(C28="","",IFERROR(INDEX(Productos!$C$5:$C$104,MATCH(C28,Productos!$B$5:$B$104,0)),"")) | G28: =IF(C28="","",IFERROR(INDEX(Productos!$G$5:$G$104,MATCH(C28,Productos!$B$5:$B$104,0)),0)) | I28: =IF(C28="","",F28*G28*(1-H28)) | L28: =IF(C28="","",F28*IFERROR(INDEX(Productos!$F$5:$F$104,MATCH(C28,Productos!$B$5:$B$104,0)),0)) | M28: =IF(C28="","",I28-L28)
D29: =IF(C29="","",IFERROR(INDEX(Productos!$A$5:$A$104,MATCH(C29,Productos!$B$5:$B$104,0)),"")) | E29: =IF(C29="","",IFERROR(INDEX(Productos!$C$5:$C$104,MATCH(C29,Productos!$B$5:$B$104,0)),"")) | G29: =IF(C29="","",IFERROR(INDEX(Productos!$G$5:$G$104,MATCH(C29,Productos!$B$5:$B$104,0)),0)) | I29: =IF(C29="","",F29*G29*(1-H29)) | L29: =IF(C29="","",F29*IFERROR(INDEX(Productos!$F$5:$F$104,MATCH(C29,Productos!$B$5:$B$104,0)),0)) | M29: =IF(C29="","",I29-L29)
D30: =IF(C30="","",IFERROR(INDEX(Productos!$A$5:$A$104,MATCH(C30,Productos!$B$5:$B$104,0)),"")) | E30: =IF(C30="","",IFERROR(INDEX(Productos!$C$5:$C$104,MATCH(C30,Productos!$B$5:$B$104,0)),"")) | G30: =IF(C30="","",IFERROR(INDEX(Productos!$G$5:$G$104,MATCH(C30,Productos!$B$5:$B$104,0)),0)) | I30: =IF(C30="","",F30*G30*(1-H30)) | L30: =IF(C30="","",F30*IFERROR(INDEX(Productos!$F$5:$F$104,MATCH(C30,Productos!$B$5:$B$104,0)),0)) | M30: =IF(C30="","",I30-L30)
D31: =IF(C31="","",IFERROR(INDEX(Productos!$A$5:$A$104,MATCH(C31,Productos!$B$5:$B$104,0)),"")) | E31: =IF(C31="","",IFERROR(INDEX(Productos!$C$5:$C$104,MATCH(C31,Productos!$B$5:$B$104,0)),"")) | G31: =IF(C31="","",IFERROR(INDEX(Productos!$G$5:$G$104,MATCH(C31,Productos!$B$5:$B$104,0)),0)) | I31: =IF(C31="","",F31*G31*(1-H31)) | L31: =IF(C31="","",F31*IFERROR(INDEX(Productos!$F$5:$F$104,MATCH(C31,Productos!$B$5:$B$104,0)),0)) | M31: =IF(C31="","",I31-L31)
D32: =IF(C32="","",IFERROR(INDEX(Productos!$A$5:$A$104,MATCH(C32,Productos!$B$5:$B$104,0)),"")) | E32: =IF(C32="","",IFERROR(INDEX(Productos!$C$5:$C$104,MATCH(C32,Productos!$B$5:$B$104,0)),"")) | G32: =IF(C32="","",IFERROR(INDEX(Productos!$G$5:$G$104,MATCH(C32,Productos!$B$5:$B$104,0)),0)) | I32: =IF(C32="","",F32*G32*(1-H32)) | L32: =IF(C32="","",F32*IFERROR(INDEX(Productos!$F$5:$F$104,MATCH(C32,Productos!$B$5:$B$104,0)),0)) | M32: =IF(C32="","",I32-L32)
... D504: =IF(C504="","",IFERROR(INDEX(Productos!$A$5:$A$104,MATCH(C504,Productos!$B$5:$B$104,0)),"")) | E504: =IF(C504="","",IFERROR(INDEX(Productos!$C$5:$C$104,MATCH(C504,Productos!$B$5:$B$104,0)),"")) | G504: =IF(C504="","",IFERROR(INDEX(Productos!$G$5:$G$104,MATCH(C504,Productos!$B$5:$B$104,0)),0)) | I504: =IF(C504="","",F504*G504*(1-H504)) | L504: =IF(C504="","",F504*IFERROR(INDEX(Productos!$F$5:$F$104,MATCH(C504,Productos!$B$5:$B$104,0)),0)) | M504: =IF(C504="","",I504-L504)

Sheet Compras
A1: Compras / Entradas de mercancía
A2: Elige el Producto en la lista y escribe Fecha y Cantidad (azul); el código, proveedor, costo y total se completan solos.
A3: TOTALES | E3: =SUM(E5:E304) -> 277 | G3: =SUM(G5:G304) -> 333.9
A4: Fecha | B4: Producto | C4: Código | D4: Proveedor | E4: Cantidad | F4: Costo unitario | G4: Total compra
A5: 46267 | B5: Arroz 1 kg | C5: =IF(B5="","",IFERROR(INDEX(Productos!$A$5:$A$104,MATCH(B5,Productos!$B$5:$B$104,0)),"")) -> P001 | D5: =IF(B5="","",IFERROR(INDEX(Productos!$D$5:$D$104,MATCH(B5,Productos!$B$5:$B$104,0)),"")) -> Distribuidora Norte | E5: 40 | F5: =IF(B5="","",IFERROR(INDEX(Productos!$F$5:$F$104,MATCH(B5,Productos!$B$5:$B$104,0)),0)) -> 0.9 | G5: =IF(B5="","",E5*F5) -> 36
A6: 46267 | B6: Leche entera 1 L | C6: =IF(B6="","",IFERROR(INDEX(Productos!$A$5:$A$104,MATCH(B6,Productos!$B$5:$B$104,0)),"")) -> P003 | D6: =IF(B6="","",IFERROR(INDEX(Productos!$D$5:$D$104,MATCH(B6,Productos!$B$5:$B$104,0)),"")) -> Lácteos del Sur | E6: 60 | F6: =IF(B6="","",IFERROR(INDEX(Productos!$F$5:$F$104,MATCH(B6,Productos!$B$5:$B$104,0)),0)) -> 0.65 | G6: =IF(B6="","",E6*F6) -> 39
A7: 46274 | B7: Refresco cola 2 L | C7: =IF(B7="","",IFERROR(INDEX(Productos!$A$5:$A$104,MATCH(B7,Productos!$B$5:$B$104,0)),"")) -> P005 | D7: =IF(B7="","",IFERROR(INDEX(Productos!$D$5:$D$104,MATCH(B7,Productos!$B$5:$B$104,0)),"")) -> Bebidas Central | E7: 30 | F7: =IF(B7="","",IFERROR(INDEX(Productos!$F$5:$F$104,MATCH(B7,Productos!$B$5:$B$104,0)),0)) -> 1 | G7: =IF(B7="","",E7*F7) -> 30
A8: 46280 | B8: Detergente 3 L | C8: =IF(B8="","",IFERROR(INDEX(Productos!$A$5:$A$104,MATCH(B8,Productos!$B$5:$B$104,0)),"")) -> P007 | D8: =IF(B8="","",IFERROR(INDEX(Productos!$D$5:$D$104,MATCH(B8,Productos!$B$5:$B$104,0)),"")) -> Hogar Plus | E8: 12 | F8: =IF(B8="","",IFERROR(INDEX(Productos!$F$5:$F$104,MATCH(B8,Productos!$B$5:$B$104,0)),0)) -> 5.2 | G8: =IF(B8="","",E8*F8) -> 62.4
A9: 46287 | B9: Galletas surtidas | C9: =IF(B9="","",IFERROR(INDEX(Productos!$A$5:$A$104,MATCH(B9,Productos!$B$5:$B$104,0)),"")) -> P009 | D9: =IF(B9="","",IFERROR(INDEX(Productos!$D$5:$D$104,MATCH(B9,Productos!$B$5:$B$104,0)),"")) -> Dulces SA | E9: 25 | F9: =IF(B9="","",IFERROR(INDEX(Productos!$F$5:$F$104,MATCH(B9,Productos!$B$5:$B$104,0)),0)) -> 1.2 | G9: =IF(B9="","",E9*F9) -> 30
A10: 46296 | B10: Agua mineral 1,5 L | C10: =IF(B10="","",IFERROR(INDEX(Productos!$A$5:$A$104,MATCH(B10,Productos!$B$5:$B$104,0)),"")) -> P006 | D10: =IF(B10="","",IFERROR(INDEX(Productos!$D$5:$D$104,MATCH(B10,Productos!$B$5:$B$104,0)),"")) -> Bebidas Central | E10: 60 | F10: =IF(B10="","",IFERROR(INDEX(Productos!$F$5:$F$104,MATCH(B10,Productos!$B$5:$B$104,0)),0)) -> 0.3 | G10: =IF(B10="","",E10*F10) -> 18
A11: 46303 | B11: Aceite de oliva 1 L | C11: =IF(B11="","",IFERROR(INDEX(Productos!$A$5:$A$104,MATCH(B11,Productos!$B$5:$B$104,0)),"")) -> P002 | D11: =IF(B11="","",IFERROR(INDEX(Productos!$D$5:$D$104,MATCH(B11,Productos!$B$5:$B$104,0)),"")) -> Distribuidora Norte | E11: 20 | F11: =IF(B11="","",IFERROR(INDEX(Productos!$F$5:$F$104,MATCH(B11,Productos!$B$5:$B$104,0)),0)) -> 4.5 | G11: =IF(B11="","",E11*F11) -> 90
A12: 46310 | B12: Patatas fritas 150 g | C12: =IF(B12="","",IFERROR(INDEX(Productos!$A$5:$A$104,MATCH(B12,Productos!$B$5:$B$104,0)),"")) -> P010 | D12: =IF(B12="","",IFERROR(INDEX(Productos!$D$5:$D$104,MATCH(B12,Productos!$B$5:$B$104,0)),"")) -> Dulces SA | E12: 30 | F12: =IF(B12="","",IFERROR(INDEX(Productos!$F$5:$F$104,MATCH(B12,Productos!$B$5:$B$104,0)),0)) -> 0.95 | G12: =IF(B12="","",E12*F12) -> 28.5
C13: =IF(B13="","",IFERROR(INDEX(Productos!$A$5:$A$104,MATCH(B13,Productos!$B$5:$B$104,0)),"")) | D13: =IF(B13="","",IFERROR(INDEX(Productos!$D$5:$D$104,MATCH(B13,Productos!$B$5:$B$104,0)),"")) | F13: =IF(B13="","",IFERROR(INDEX(Productos!$F$5:$F$104,MATCH(B13,Productos!$B$5:$B$104,0)),0)) | G13: =IF(B13="","",E13*F13)
C14: =IF(B14="","",IFERROR(INDEX(Productos!$A$5:$A$104,MATCH(B14,Productos!$B$5:$B$104,0)),"")) | D14: =IF(B14="","",IFERROR(INDEX(Productos!$D$5:$D$104,MATCH(B14,Productos!$B$5:$B$104,0)),"")) | F14: =IF(B14="","",IFERROR(INDEX(Productos!$F$5:$F$104,MATCH(B14,Productos!$B$5:$B$104,0)),0)) | G14: =IF(B14="","",E14*F14)
C15: =IF(B15="","",IFERROR(INDEX(Productos!$A$5:$A$104,MATCH(B15,Productos!$B$5:$B$104,0)),"")) | D15: =IF(B15="","",IFERROR(INDEX(Productos!$D$5:$D$104,MATCH(B15,Productos!$B$5:$B$104,0)),"")) | F15: =IF(B15="","",IFERROR(INDEX(Productos!$F$5:$F$104,MATCH(B15,Productos!$B$5:$B$104,0)),0)) | G15: =IF(B15="","",E15*F15)
C16: =IF(B16="","",IFERROR(INDEX(Productos!$A$5:$A$104,MATCH(B16,Productos!$B$5:$B$104,0)),"")) | D16: =IF(B16="","",IFERROR(INDEX(Productos!$D$5:$D$104,MATCH(B16,Productos!$B$5:$B$104,0)),"")) | F16: =IF(B16="","",IFERROR(INDEX(Productos!$F$5:$F$104,MATCH(B16,Productos!$B$5:$B$104,0)),0)) | G16: =IF(B16="","",E16*F16)
C17: =IF(B17="","",IFERROR(INDEX(Productos!$A$5:$A$104,MATCH(B17,Productos!$B$5:$B$104,0)),"")) | D17: =IF(B17="","",IFERROR(INDEX(Productos!$D$5:$D$104,MATCH(B17,Productos!$B$5:$B$104,0)),"")) | F17: =IF(B17="","",IFERROR(INDEX(Productos!$F$5:$F$104,MATCH(B17,Productos!$B$5:$B$104,0)),0)) | G17: =IF(B17="","",E17*F17)
C18: =IF(B18="","",IFERROR(INDEX(Productos!$A$5:$A$104,MATCH(B18,Productos!$B$5:$B$104,0)),"")) | D18: =IF(B18="","",IFERROR(INDEX(Productos!$D$5:$D$104,MATCH(B18,Productos!$B$5:$B$104,0)),"")) | F18: =IF(B18="","",IFERROR(INDEX(Productos!$F$5:$F$104,MATCH(B18,Productos!$B$5:$B$104,0)),0)) | G18: =IF(B18="","",E18*F18)
C19: =IF(B19="","",IFERROR(INDEX(Productos!$A$5:$A$104,MATCH(B19,Productos!$B$5:$B$104,0)),"")) | D19: =IF(B19="","",IFERROR(INDEX(Productos!$D$5:$D$104,MATCH(B19,Productos!$B$5:$B$104,0)),"")) | F19: =IF(B19="","",IFERROR(INDEX(Productos!$F$5:$F$104,MATCH(B19,Productos!$B$5:$B$104,0)),0)) | G19: =IF(B19="","",E19*F19)
C20: =IF(B20="","",IFERROR(INDEX(Productos!$A$5:$A$104,MATCH(B20,Productos!$B$5:$B$104,0)),"")) | D20: =IF(B20="","",IFERROR(INDEX(Productos!$D$5:$D$104,MATCH(B20,Productos!$B$5:$B$104,0)),"")) | F20: =IF(B20="","",IFERROR(INDEX(Productos!$F$5:$F$104,MATCH(B20,Productos!$B$5:$B$104,0)),0)) | G20: =IF(B20="","",E20*F20)
C21: =IF(B21="","",IFERROR(INDEX(Productos!$A$5:$A$104,MATCH(B21,Productos!$B$5:$B$104,0)),"")) | D21: =IF(B21="","",IFERROR(INDEX(Productos!$D$5:$D$104,MATCH(B21,Productos!$B$5:$B$104,0)),"")) | F21: =IF(B21="","",IFERROR(INDEX(Productos!$F$5:$F$104,MATCH(B21,Productos!$B$5:$B$104,0)),0)) | G21: =IF(B21="","",E21*F21)
C22: =IF(B22="","",IFERROR(INDEX(Productos!$A$5:$A$104,MATCH(B22,Productos!$B$5:$B$104,0)),"")) | D22: =IF(B22="","",IFERROR(INDEX(Productos!$D$5:$D$104,MATCH(B22,Productos!$B$5:$B$104,0)),"")) | F22: =IF(B22="","",IFERROR(INDEX(Productos!$F$5:$F$104,MATCH(B22,Productos!$B$5:$B$104,0)),0)) | G22: =IF(B22="","",E22*F22)
C23: =IF(B23="","",IFERROR(INDEX(Productos!$A$5:$A$104,MATCH(B23,Productos!$B$5:$B$104,0)),"")) | D23: =IF(B23="","",IFERROR(INDEX(Productos!$D$5:$D$104,MATCH(B23,Productos!$B$5:$B$104,0)),"")) | F23: =IF(B23="","",IFERROR(INDEX(Productos!$F$5:$F$104,MATCH(B23,Productos!$B$5:$B$104,0)),0)) | G23: =IF(B23="","",E23*F23)
C24: =IF(B24="","",IFERROR(INDEX(Productos!$A$5:$A$104,MATCH(B24,Productos!$B$5:$B$104,0)),"")) | D24: =IF(B24="","",IFERROR(INDEX(Productos!$D$5:$D$104,MATCH(B24,Productos!$B$5:$B$104,0)),"")) | F24: =IF(B24="","",IFERROR(INDEX(Productos!$F$5:$F$104,MATCH(B24,Productos!$B$5:$B$104,0)),0)) | G24: =IF(B24="","",E24*F24)
... C304: =IF(B304="","",IFERROR(INDEX(Productos!$A$5:$A$104,MATCH(B304,Productos!$B$5:$B$104,0)),"")) | D304: =IF(B304="","",IFERROR(INDEX(Productos!$D$5:$D$104,MATCH(B304,Productos!$B$5:$B$104,0)),"")) | F304: =IF(B304="","",IFERROR(INDEX(Productos!$F$5:$F$104,MATCH(B304,Productos!$B$5:$B$104,0)),0)) | G304: =IF(B304="","",E304*F304)

Sheet Config
A1: Configuración
A2: Celdas en azul = editables. Todo el libro usa estos valores.
A3: Nombre de la tienda | B3: Mi Tienda | D3: Categorías | F3: Métodos de pago
A4: Año de análisis | B4: 2026 | D4: Alimentos | F4: Efectivo
D5: Lácteos | F5: Transferencia
D6: Bebidas
D7: Limpieza
D8: Snacks
D9: Papelería
D10: Higiene personal
D11: Otros
